{
    "background": "phantasia:aridra",
    "map_colour": "#F4AF66",
    "sky_colour": {
        "dawn": {
            "base": "#292231",
            "gradient": "#37232C"
        },
        "day": {
            "base": "#D3BEA9",
            "gradient": "#936E63"
        },
        "dusk": {
            "base": "#C66448",
            "gradient": "#AC6F56"
        },
        "night": {
            "base": "#17121D",
            "gradient": "#110A14"
        }
    },
    "light_colour": {
        "dawn": "#C68B69",
        "day": "#FFFFFF",
        "dusk": "#C68B69",
        "night": "#141B35"
    },
    "music": [
        {
            "id": "phantasia:dune",
            "gain": 0.3
        },
        {
            "id": "phantasia:field_of_concourse",
            "gain": 0.4
        },
        {
            "id": "phantasia:oasis",
            "gain": 0.4
        },
        {
            "id": "phantasia:sol_y_luna",
            "gain": 0.5
        },
        {
            "id": "phantasia:tense",
            "gain": 0.5
        }
    ],
	"tile": {
		"top_layer": {
			"base": {
				"id": "phantasia:sand"
			},
			"wall": {
				"id": "phantasia:sandstone_wall"
			}
		},
		"sub_layer": {
            "base": {
                "id": "phantasia:sand"
            },
            "wall": {
                "id": "phantasia:sandstone_wall"
            }
		}
	},
    "creature": [
        {
            "id": "phantasia:chicken",
            "variant": "warm",
            "amount": 1,
            "chance": 0.01,
            "time": {
                "min": 0,
                "max": 890
            },
            "tile": "#phantasia:tile/creature_spawn/animal"
        }
    ],
    "foliage": [
        {
            "id": "phantasia:short_grass_dry",
            "chance": 0.14,
            "placeable_on": "#phantasia:tile/placement/dry_plant_on"
        },
        {
            "id": "phantasia:tall_grass_dry",
            "chance": 0.06,
            "placeable_on": "#phantasia:tile/placement/dry_plant_on"
        },
        {
            "id": "phantasia:dead_bush",
            "chance": 0.12,
            "placeable_on": [ "phantasia:sand" ]
        },
        {
            "id": "phantasia:rock",
            "chance": 0.04,
            "placeable_on": [ "phantasia:sand" ]
        },
        {
            "id": "phantasia:twig",
            "chance": 0.05,
            "placeable_on": [ "phantasia:sand" ]
        }
    ],
    "structure": [
        {
            "id": "phantasia:tall_foliage/cactus",
            "chance": 0.06,
            "placeable_on": "#phantasia:tile/placement/plant_on"
        }
    ]
}